jsonsql/__init__.py
jsonsql/jsonsql.py
jsonsql-1.1.4.dist-info/METADATA
jsonsql-1.1.4.dist-info/WHEEL
jsonsql-1.1.4.dist-info/licenses/LICENSE
jsonsql-1.1.4.dist-info/RECORD
