Metadata-Version: 2.3
Name: jsonsql
Version: 1.1.4
Summary: A way to accept SQL input with sanitization and parameterization with a json format
Project-URL: Homepage, https://github.com/BigBrainTime/JsonSQL
Project-URL: Issues, https://github.com/BigBrainTime/JsonSQL/issues
Author: BigBrainTime
License-File: LICENSE
Classifier: License :: OSI Approved :: MIT License
Classifier: Operating System :: OS Independent
Classifier: Programming Language :: Python :: 3
Requires-Python: >=3.10
